README.rst
setup.cfg
setup.py
dialogue.multi_method.egg-info/PKG-INFO
dialogue.multi_method.egg-info/SOURCES.txt
dialogue.multi_method.egg-info/dependency_links.txt
dialogue.multi_method.egg-info/requires.txt
dialogue.multi_method.egg-info/top_level.txt
dialogue/multi_method/__init__.py