Metadata-Version: 1.0
Name: dialogue.multi-method
Version: 0.0.5
Summary: UNKNOWN
Home-page: https://github.com/dialoguemd/multi-method
Author: Hugo Duncan
Author-email: hugo.duncan@dialogue.co
License: UNKNOWN
Platform: UNKNOWN
